MdnHtmlWendang20170730/README.md
MdnHtmlWendang20170730/__init__.py
MdnHtmlWendang20170730/__main__.py
MdnHtmlWendang20170730/file.epub
MdnHtmlWendang20170730/index.html
MdnHtmlWendang20170730/css/__init__.py
MdnHtmlWendang20170730/css/annotations.css
MdnHtmlWendang20170730/css/main.css
MdnHtmlWendang20170730/css/normalize.css
MdnHtmlWendang20170730/css/popup.css
MdnHtmlWendang20170730/font/__init__.py
MdnHtmlWendang20170730/font/fontello.eot
MdnHtmlWendang20170730/font/fontello.svg
MdnHtmlWendang20170730/font/fontello.ttf
MdnHtmlWendang20170730/font/fontello.woff
MdnHtmlWendang20170730/img/__init__.py
MdnHtmlWendang20170730/img/annotator-glyph-sprite.png
MdnHtmlWendang20170730/img/annotator-icon-sprite.png
MdnHtmlWendang20170730/img/apple-touch-icon.png
MdnHtmlWendang20170730/img/cancelfullscreen.png
MdnHtmlWendang20170730/img/close.png
MdnHtmlWendang20170730/img/fullscreen.png
MdnHtmlWendang20170730/img/loader.gif
MdnHtmlWendang20170730/img/menu-icon.png
MdnHtmlWendang20170730/img/save.png
MdnHtmlWendang20170730/img/saved.png
MdnHtmlWendang20170730/img/settings-s.png
MdnHtmlWendang20170730/img/settings.png
MdnHtmlWendang20170730/img/star.png
MdnHtmlWendang20170730/js/__init__.py
MdnHtmlWendang20170730/js/epub.js
MdnHtmlWendang20170730/js/epub.min.js
MdnHtmlWendang20170730/js/epub.min.map
MdnHtmlWendang20170730/js/hooks.min.js
MdnHtmlWendang20170730/js/hooks.min.map
MdnHtmlWendang20170730/js/reader.js
MdnHtmlWendang20170730/js/reader.js.map
MdnHtmlWendang20170730/js/reader.min.js
MdnHtmlWendang20170730/js/reader.min.map
MdnHtmlWendang20170730/js/hooks/__init__.py
MdnHtmlWendang20170730/js/hooks/extensions/__init__.py
MdnHtmlWendang20170730/js/hooks/extensions/highlight.js
MdnHtmlWendang20170730/js/libs/__init__.py
MdnHtmlWendang20170730/js/libs/jquery.min.js
MdnHtmlWendang20170730/js/libs/localforage.min.js
MdnHtmlWendang20170730/js/libs/screenfull.js
MdnHtmlWendang20170730/js/libs/screenfull.min.js
MdnHtmlWendang20170730/js/libs/zip.min.js
mdn_html_wendang_20170730-2024.3.2.0.dist-info/METADATA
mdn_html_wendang_20170730-2024.3.2.0.dist-info/WHEEL
mdn_html_wendang_20170730-2024.3.2.0.dist-info/entry_points.txt
mdn_html_wendang_20170730-2024.3.2.0.dist-info/top_level.txt
mdn_html_wendang_20170730-2024.3.2.0.dist-info/RECORD
